DataPulse/Energy_consumption_data.py
DataPulse/Environmental_data.py
DataPulse/HR_data.py
DataPulse/IOT_data.py
DataPulse/IT_infrastructure_data.py
DataPulse/Insurance_data.py
DataPulse/Investment_data.py
DataPulse/Manufacturing_data.py
DataPulse/NLP_data.py
DataPulse/SupplyChain_data.py
DataPulse/Traffic_accident.py
DataPulse/__init__.py
DataPulse/agriculture_data.py
DataPulse/assets_data.py
DataPulse/audio_data.py
DataPulse/banking_transaction.py
DataPulse/biometric_data.py
DataPulse/call_center_data.py
DataPulse/copyright_data.py
DataPulse/customer_data.py
DataPulse/cybersecurity_data.py
DataPulse/demographics_data.py
DataPulse/e-commerce_data.py
DataPulse/educational_data.py
DataPulse/financial_data.py
DataPulse/food_supply_chain.py
DataPulse/gaming_data.py
DataPulse/genomic_data.py
DataPulse/geospatial_data.py
DataPulse/governmentsector_data.py
DataPulse/image_data.py
DataPulse/legal_compliance_data.py
DataPulse/livestock_data.py
DataPulse/logistic_data.py
DataPulse/maritime_data.py
DataPulse/marketing_data.py
DataPulse/medical_data.py
DataPulse/online_learning_data.py
DataPulse/pension_data.py
DataPulse/real_state_data.py
DataPulse/retail_data.py
DataPulse/sales_data.py
DataPulse/sentiment_data.py
DataPulse/social_media_data.py
DataPulse/supports_data.py
DataPulse/survey_data.py
DataPulse/telecom_data.py
DataPulse/transport_data.py
DataPulse/urban_development.py
DataPulse/video_data.py
DataPulse/weather_data.py
DataPulse/wildlife_data.py
datrix-1.1.0.dist-info/LICENSE
datrix-1.1.0.dist-info/METADATA
datrix-1.1.0.dist-info/WHEEL
datrix-1.1.0.dist-info/top_level.txt
datrix-1.1.0.dist-info/RECORD
